cloud_data_connector/__init__.py
cloud_data_connector/aws/README.md
cloud_data_connector/aws/__init__.py
cloud_data_connector/aws/connector.py
cloud_data_connector/aws/downloader.py
cloud_data_connector/aws/uploader.py
cloud_data_connector/azure/.gitattributes
cloud_data_connector/azure/AzureML.md
cloud_data_connector/azure/README.md
cloud_data_connector/azure/__init__.py
cloud_data_connector/azure/connector.py
cloud_data_connector/azure/connector_object.py
cloud_data_connector/azure/downloader.py
cloud_data_connector/azure/ml_uploader.py
cloud_data_connector/azure/uploader.py
cloud_data_connector/gcp/README.md
cloud_data_connector/gcp/__init__.py
cloud_data_connector/gcp/connector.py
cloud_data_connector/gcp/downloader.py
cloud_data_connector/gcp/query.py
cloud_data_connector/gcp/uploader.py
cloud_data_connector/int/__init__.py
cloud_data_connector/int/int_connector.py
cloud_data_connector/int/int_downloader.py
cloud_data_connector/int/int_uploader.py
cloud_data_connector-1.0.3.dist-info/LICENSE
cloud_data_connector-1.0.3.dist-info/METADATA
cloud_data_connector-1.0.3.dist-info/WHEEL
cloud_data_connector-1.0.3.dist-info/top_level.txt
cloud_data_connector-1.0.3.dist-info/RECORD
