Metadata-Version: 2.1
Name: cloud_data_connector
Version: 1.0.3
Summary: Intel's cloud data connector
Author-email: IntelAI <IntelAI@intel.com>
License: 
Classifier: License :: OSI Approved :: Apache Software License
Classifier: Programming Language :: Python :: 3
Classifier: Programming Language :: Python :: 3.9
Classifier: Programming Language :: Python :: 3.10
Classifier: Operating System :: OS Independent
Requires-Python: <3.11,>=3.9
License-File: LICENSE
Requires-Dist: azureml >=0.2.7
Requires-Dist: azure-ai-ml >=1.4.0
Requires-Dist: azureml-core >=1.49.0
Requires-Dist: azure-identity >=1.12.0
Requires-Dist: azure-storage-blob >=1.4.1
Requires-Dist: azure-core >=1.26.3
Requires-Dist: boto3 >=1.26.154
Requires-Dist: google-api-core >=2.0.0
Requires-Dist: google-auth >=1.33.0
Requires-Dist: google-auth-oauthlib >=0.4.1
Requires-Dist: google-cloud-bigquery >=2.1.0
Requires-Dist: google-cloud-storage >=2.1.0
Requires-Dist: packaging >=21.3
Requires-Dist: python-dotenv >=1.0.0
